resultify/__init__.py
resultify/py.typed
resultify-1.3.1.dist-info/LICENSE
resultify-1.3.1.dist-info/METADATA
resultify-1.3.1.dist-info/WHEEL
resultify-1.3.1.dist-info/top_level.txt
resultify-1.3.1.dist-info/zip-safe
resultify-1.3.1.dist-info/RECORD
