Metadata-Version: 2.1
Name: resultify
Version: 1.3.1
Summary: A rust-like result type for Python
Home-page: https://github.com/felixhammerl/resultify
Author: Felix Hammerl
Author-email: felix.hammerl@gmail.com
Keywords: rust result
Classifier: Development Status :: 5 - Production/Stable
Classifier: Intended Audience :: Developers
Classifier: License :: OSI Approved :: MIT License
Classifier: Programming Language :: Python :: 3
Classifier: Programming Language :: Python :: 3 :: Only
Classifier: Programming Language :: Python :: 3.8
Classifier: Programming Language :: Python :: 3.9
Classifier: Programming Language :: Python :: 3.10
Classifier: Programming Language :: Python :: 3.11
Classifier: Programming Language :: Python :: 3.12
Requires-Python: >=3.8
License-File: LICENSE
